CHANGES.rst
MANIFEST.in
README.rst
setup.py
tests-req.txt
redis2hdfs/__init__.py
redis2hdfs/redis2hdfs.py
redis2hdfs.egg-info/PKG-INFO
redis2hdfs.egg-info/SOURCES.txt
redis2hdfs.egg-info/dependency_links.txt
redis2hdfs.egg-info/entry_points.txt
redis2hdfs.egg-info/not-zip-safe
redis2hdfs.egg-info/requires.txt
redis2hdfs.egg-info/top_level.txt