Metadata-Version: 1.1
Name: redis2hdfs
Version: 0.0.1
Summary: Export Redis data to HDFS
Home-page: https://github.com/xiaogaozi/redis2hdfs
Author: xiaogaozi
Author-email: gaochangjian@gmail.com
License: MIT License
Keywords: redis hdfs
Platform: UNKNOWN
Classifier: Development Status :: 4 - Beta
Classifier: Environment :: Console
Classifier: Intended Audience :: System Administrators
Classifier: License :: OSI Approved :: MIT License
Classifier: Operating System :: OS Independent
Classifier: Programming Language :: Python :: 2
Classifier: Programming Language :: Python :: 2.6
Classifier: Programming Language :: Python :: 2.7
Classifier: Topic :: Utilities
